{
  "type": "product",
  "currency": "EUR",
  "itemName": "MCoBeauty Highlight & Glow Champagne Glow Beauty Wand",
  "code": "6317036",
  "price": "5.99",
  "priceOriginal": "11.99",
  "itemBgbcat": "2002 > 2069 > 2210 > 2378 > 2819 > 6780",
  "supplier": "VIDACORP NETHERLANDS B.V.",
  "inStock": "inStock",
  "onPromo": "3032979",
  "mmkId": "3032979",
  "productGroupId": "513947",
  "brandType": "Exclusief merk",
  "discount": "€ 6,00",
  "url": "/mcobeauty-highlight-glow-champagne-glow-beauty-wand/p/6317036",
  "listName": "Lister",
  "brand": "MCoBeauty",
  "mpOrigin": "Kruidvat",
  "mpShopId": "1",
  "isSponsored": "false",
  "categories": [
    {
      "id": 29536622,
      "name": "Beauty"
    },
    {
      "id": 30267038,
      "name": "Make-up"
    },
    {
      "id": 30267146,
      "name": "Highlighter"
    }
  ],
  "description": "12ml",
  "image": "/medias/sys_master/prd-images/hd4/hcf/34869807939614/prd-front-6317036-1_600x600/prd-front-6317036-1-600x600.jpg"
}