{
  "type": "product",
  "currency": "EUR",
  "itemName": "Mycosan Hielklovenzalf",
  "code": "6238874",
  "price": "15.95",
  "priceOriginal": "",
  "itemBgbcat": "2006 > 2052 > 2175 > 2429 > 6459 > 6460",
  "supplier": "OTC MEDICAL BV",
  "inStock": "inStock",
  "onPromo": "3007554",
  "mmkId": "3007554",
  "productGroupId": "",
  "brandType": "Ander merk",
  "discount": "",
  "url": "/mycosan-hielklovenzalf/p/6238874",
  "listName": "Lister",
  "brand": "Mycosan",
  "mpOrigin": "Kruidvat",
  "mpShopId": "1",
  "isSponsored": "false",
  "categories": [
    {
      "id": 29536624,
      "name": "Gezondheid"
    },
    {
      "id": 48237361,
      "name": "Voetverzorging"
    },
    {
      "id": 49316313,
      "name": "Voetkloven"
    }
  ],
  "description": "75ml",
  "image": "/medias/sys_master/prd-images/hc4/h7f/34261836333086/prd-front-6238874-1_600x600/prd-front-6238874-1-600x600.jpg"
}