{
  "type": "product",
  "currency": "EUR",
  "itemName": "Maybelline New York Build-A-Brow 260 Deep Brown Wenkbrauwpotlood en -Gel",
  "code": "5994539",
  "price": "17.99",
  "priceOriginal": "",
  "itemBgbcat": "2002 > 2069 > 2210 > 2422 > 6131 > 6132",
  "supplier": "MAYBELLINE MAKE-UP",
  "inStock": "inStock",
  "onPromo": "3029139",
  "mmkId": "3029139",
  "productGroupId": "475932",
  "brandType": "A of B merk",
  "discount": "",
  "url": "/maybelline-new-york-build-a-brow-260-deep-brown-wenkbrauwpotlood-en-gel/p/5994539",
  "listName": "Lister",
  "brand": "Maybelline",
  "mpOrigin": "Kruidvat",
  "mpShopId": "1",
  "isSponsored": "false",
  "categories": [
    {
      "id": 29536622,
      "name": "Beauty"
    },
    {
      "id": 30267038,
      "name": "Make-up"
    },
    {
      "id": 30267149,
      "name": "Wenkbrauw make-up"
    },
    {
      "id": 30267464,
      "name": "Wenkbrauwgel"
    }
  ],
  "description": "",
  "image": "/medias/sys_master/prd-images/hb8/h6d/29992812183582/prd-front-5994539-1_600x600/prd-front-5994539-1-600x600.jpg"
}