{
  "type": "product",
  "currency": "EUR",
  "itemName": "Montagne Jeunesse Green Tea Bubble Sheet Masker",
  "code": "5616668",
  "price": "12.45",
  "priceOriginal": "",
  "itemBgbcat": "2002 > 2089 > 2256 > 2301 > 2775 > 3477",
  "supplier": "REBRO COSMETICS BV",
  "inStock": "inStock",
  "onPromo": "3033699",
  "mmkId": "3033699",
  "productGroupId": "516941",
  "brandType": "A of B merk",
  "discount": "",
  "url": "/montagne-jeunesse-green-tea-bubble-sheet-masker/p/5616668",
  "listName": "Lister",
  "brand": "7th Heaven",
  "mpOrigin": "Kruidvat",
  "mpShopId": "1",
  "isSponsored": "false",
  "categories": [
    {
      "id": 29536622,
      "name": "Beauty"
    },
    {
      "id": 30267042,
      "name": "Skincare"
    },
    {
      "id": 30267164,
      "name": "Gezichtsmaskers"
    }
  ],
  "description": "5 stuks, alle huidtypes",
  "image": "/medias/sys_master/prd-images/hc1/h79/28553151709214/prd-front-5616668-1_600x600/prd-front-5616668-1-600x600.jpg"
}