{
  "type": "product",
  "currency": "EUR",
  "itemName": "SYOSS Donker Bruin Uitgroeispray",
  "code": "4078670",
  "price": "12.49",
  "priceOriginal": "",
  "itemBgbcat": "2003 > 2058 > 2187 > 2376 > 2817 > 4025",
  "supplier": "HENKEL NEDERLAND BV U-K",
  "inStock": "inStock",
  "onPromo": "3030561",
  "mmkId": "3030561",
  "productGroupId": "485573",
  "brandType": "A of B merk",
  "discount": "",
  "url": "/syoss-donker-bruin-uitgroeispray/p/4078670",
  "listName": "Lister",
  "brand": "Syoss",
  "mpOrigin": "Kruidvat",
  "mpShopId": "1",
  "isSponsored": "false",
  "categories": [
    {
      "id": 29536622,
      "name": "Beauty"
    },
    {
      "id": 30267041,
      "name": "Haarverf"
    }
  ],
  "description": "",
  "image": "/medias/sys_master/prd-images/h2a/hef/32891203813406/prd-front-4078670-1_600x600/prd-front-4078670-1-600x600.jpg"
}