{
  "type": "product",
  "currency": "EUR",
  "itemName": "NIVEA Sun Kids Protect & Hydrate SPF50+ Zonnebrand Roll-on",
  "code": "4055493",
  "price": "14.49",
  "priceOriginal": "",
  "itemBgbcat": "2003 > 2093 > 2264 > 2623 > 2702 > 3405",
  "supplier": "BEIERSDORF NV NL",
  "inStock": "inStock",
  "onPromo": "3030124",
  "mmkId": "3030124",
  "productGroupId": "483894",
  "brandType": "A of B merk",
  "discount": "",
  "url": "/nivea-sun-kids-protect-hydrate-spf50-zonnebrand-roll-on/p/4055493",
  "listName": "Lister",
  "brand": "Nivea Sun",
  "mpOrigin": "Kruidvat",
  "mpShopId": "1",
  "isSponsored": "false",
  "categories": [
    {
      "id": 29536623,
      "name": "Verzorging"
    },
    {
      "id": 30267050,
      "name": "Zonbescherming"
    },
    {
      "id": 30267214,
      "name": "Zonnebrand"
    }
  ],
  "description": "50ml",
  "image": "/medias/sys_master/prd-images/hce/hf1/34393580142622/prd-front-4055493-1_600x600/prd-front-4055493-1-600x600.jpg"
}