{
  "type": "product",
  "currency": "EUR",
  "itemName": "NIVEA Q10 Verstevigend + Anti-Rimpel Crème voor Hals en Decolleté",
  "code": "6285858",
  "price": "21.69",
  "priceOriginal": "",
  "itemBgbcat": "2003 > 2059 > 2139 > 2342 > 3036 > 3484",
  "supplier": "BEIERSDORF NV NL",
  "inStock": "inStock",
  "onPromo": "3032227",
  "mmkId": "3032227",
  "productGroupId": "473518",
  "brandType": "A of B merk",
  "discount": "",
  "url": "/nivea-q10-verstevigend-anti-rimpel-creme-voor-hals-en-decollete/p/6285858",
  "listName": "Lister",
  "brand": "Nivea",
  "mpOrigin": "Kruidvat",
  "mpShopId": "1",
  "isSponsored": "false",
  "categories": [
    {
      "id": 29536622,
      "name": "Beauty"
    },
    {
      "id": 30267042,
      "name": "Skincare"
    },
    {
      "id": 30267159,
      "name": "Dagcreme"
    }
  ],
  "description": "200ml"
}