{
  "type": "product",
  "currency": "EUR",
  "itemName": "e.l.f. Universal Sheer Matte Putty Primer",
  "code": "6275778",
  "price": "13.0",
  "priceOriginal": "",
  "itemBgbcat": "2002 > 2069 > 2210 > 2378 > 2819 > 6782",
  "supplier": "ELF BEAUTY UK LIMITED",
  "inStock": "inStock",
  "onPromo": "",
  "mmkId": "",
  "productGroupId": "",
  "brandType": "A of B merk",
  "discount": "",
  "url": "/elf-universal-sheer-matte-putty-primer/p/6275778",
  "listName": "Lister",
  "brand": "ELF",
  "mpOrigin": "Kruidvat",
  "mpShopId": "1",
  "isSponsored": "false",
  "categories": [
    {
      "id": 29536622,
      "name": "Beauty"
    },
    {
      "id": 30267038,
      "name": "Make-up"
    },
    {
      "id": 30267136,
      "name": "Primer"
    }
  ],
  "description": "21g",
  "image": "/medias/sys_master/prd-images/h2d/hae/34039572693022/prd-front-6275778-1_600x600/prd-front-6275778-1-600x600.jpg"
}