{
  "type": "product",
  "currency": "EUR",
  "itemName": "Rimmel London Extra Super Lash 102 Brown Black Mascara",
  "code": "5060322",
  "price": "11.99",
  "priceOriginal": "",
  "itemBgbcat": "2002 > 2069 > 2210 > 2422 > 3016 > 3840",
  "supplier": "COTY NETHERLANDS BV CB",
  "inStock": "inStock",
  "onPromo": "3028409",
  "mmkId": "3028409",
  "productGroupId": "472676",
  "brandType": "A of B merk",
  "discount": "",
  "url": "/rimmel-london-extra-super-lash-102-brown-black-mascara/p/5060322",
  "listName": "Lister",
  "brand": "Rimmel",
  "mpOrigin": "Kruidvat",
  "mpShopId": "1",
  "isSponsored": "false",
  "categories": [
    {
      "id": 29536622,
      "name": "Beauty"
    },
    {
      "id": 30267038,
      "name": "Make-up"
    },
    {
      "id": 30267133,
      "name": "Mascara"
    }
  ],
  "description": "8ml"
}