{
  "type": "product",
  "currency": "EUR",
  "itemName": "MCoBeauty Shimmer Lip Plump Chilli Dusty Rose 4-in-1 Hydrating Lacquer",
  "code": "6318562",
  "price": "7.99",
  "priceOriginal": "",
  "itemBgbcat": "2002 > 2069 > 2210 > 2468 > 2994 > 3821",
  "supplier": "VIDACORP NETHERLANDS B.V.",
  "inStock": "inStock",
  "onPromo": "3005772",
  "mmkId": "3005772",
  "productGroupId": "",
  "brandType": "Exclusief merk",
  "discount": "",
  "url": "/mcobeauty-shimmer-lip-plump-chilli-dusty-rose-4-in-1-hydrating-lacquer/p/6318562",
  "listName": "Lister",
  "brand": "MCoBeauty",
  "mpOrigin": "Kruidvat",
  "mpShopId": "1",
  "isSponsored": "false",
  "categories": [
    {
      "id": 29536622,
      "name": "Beauty"
    },
    {
      "id": 30267038,
      "name": "Make-up"
    },
    {
      "id": 88118383,
      "name": "Lipmake-up"
    },
    {
      "id": 88118430,
      "name": "Lip plumper"
    }
  ],
  "description": "2g",
  "image": "/medias/sys_master/prd-images/h4f/h11/35107132735518/prd-front-6318562-1_600x600/prd-front-6318562-1-600x600.jpg"
}