{
  "type": "product",
  "currency": "EUR",
  "itemName": "Lucovitaal K2 75 Mcg + D3 20 Mcg Capsules",
  "code": "5944118",
  "price": "14.99",
  "priceOriginal": "",
  "itemBgbcat": "2006 > 5048 > 2280 > 6206 > 6224 > 6298",
  "supplier": "PK BENELUX BV",
  "inStock": "inStock",
  "onPromo": "3032306",
  "mmkId": "3032306",
  "productGroupId": "497549",
  "brandType": "A of B merk",
  "discount": "",
  "url": "/lucovitaal-k2-75-mcg-d3-20-mcg-capsules/p/5944118",
  "listName": "Lister",
  "brand": "Lucovitaal",
  "mpOrigin": "Kruidvat",
  "mpShopId": "1",
  "isSponsored": "false",
  "categories": [
    {
      "id": 29536624,
      "name": "Gezondheid"
    },
    {
      "id": 30267058,
      "name": "Voedingssupplementen"
    },
    {
      "id": 30267283,
      "name": "Vitamines"
    },
    {
      "id": 30267550,
      "name": "Vitamine D"
    }
  ],
  "description": "60 stuks"
}