{
  "type": "product",
  "currency": "EUR",
  "itemName": "Philips Avent Soother Air 18M+ SCF349/47 fopspeen",
  "code": "6386742",
  "price": "8.99",
  "priceOriginal": "",
  "itemBgbcat": "2001 > 2033 > 2128 > 2417 > 2871 > 6356",
  "supplier": "PHILIPS CONSUMER LIFESTYLE BV",
  "inStock": "inStock",
  "onPromo": "3033879",
  "mmkId": "3033879",
  "productGroupId": "513822",
  "brandType": "A of B merk",
  "discount": "",
  "url": "/philips-avent-soother-air-18m-scf349/47-fopspeen/p/6386742",
  "listName": "Lister",
  "brand": "Philips Avent",
  "mpOrigin": "Kruidvat",
  "mpShopId": "1",
  "isSponsored": "false",
  "categories": [
    {
      "id": 29536625,
      "name": "Baby"
    },
    {
      "id": 30267073,
      "name": "Babyvoedingsaccessoires"
    },
    {
      "id": 30267354,
      "name": "Fopspenen"
    }
  ],
  "description": "2 stuks",
  "image": "/medias/sys_master/prd-images/hb1/h6c/44557380780062/prd-front-6386742-1_600x600/prd-front-6386742-1-600x600.jpg"
}