{
  "type": "product",
  "currency": "EUR",
  "itemName": "L'Oréal Paris Magic BB Very Light 5-in-1 Transforming Skin Corrector",
  "code": "4763536",
  "price": "8.49",
  "priceOriginal": "16.99",
  "itemBgbcat": "2002 > 2069 > 2210 > 2378 > 2819 > 3560",
  "supplier": "L'OREAL MAKE-UP",
  "inStock": "outOfStock",
  "onPromo": "3033407",
  "mmkId": "3033407",
  "productGroupId": "514775",
  "brandType": "A of B merk",
  "discount": "€ 8,50",
  "url": "/loreal-paris-magic-bb-very-light-5-in-1-transforming-skin-corrector/p/4763536",
  "listName": "Lister",
  "brand": "L'Oreal",
  "mpOrigin": "Kruidvat",
  "mpShopId": "1",
  "isSponsored": "false",
  "categories": [
    {
      "id": 29536622,
      "name": "Beauty"
    },
    {
      "id": 30267038,
      "name": "Make-up"
    },
    {
      "id": 30267138,
      "name": "CC cream"
    }
  ],
  "description": "30ml"
}