{
  "type": "product",
  "currency": "EUR",
  "itemName": "Dr. Scholl’s Voetvijl voor Harde Huid",
  "code": "6107477",
  "price": "9.99",
  "priceOriginal": "",
  "itemBgbcat": "2006 > 2052 > 2175 > 2429 > 2683 > 3383",
  "supplier": "PIETERCIL BARENDS BV",
  "inStock": "inStock",
  "onPromo": "3033915",
  "mmkId": "3033915",
  "productGroupId": "515886",
  "brandType": "A of B merk",
  "discount": "",
  "url": "/dr-scholls-voetvijl-voor-harde-huid/p/6107477",
  "listName": "Lister",
  "brand": "Dr. Scholl's",
  "mpOrigin": "Kruidvat",
  "mpShopId": "1",
  "isSponsored": "false",
  "categories": [
    {
      "id": 29536624,
      "name": "Gezondheid"
    },
    {
      "id": 48237361,
      "name": "Voetongemakken"
    },
    {
      "id": 48237442,
      "name": "Eeltverwijderaars"
    }
  ],
  "description": "",
  "image": "/medias/sys_master/prd-images/h57/h98/34313171075102/prd-front-6107477-1_600x600/prd-front-6107477-1-600x600.jpg"
}