{
  "type": "product",
  "currency": "EUR",
  "itemName": "Banzai Splash Sprinkler Waterpark",
  "code": "6458044",
  "price": "11.99",
  "priceOriginal": "",
  "itemBgbcat": "5921 > 6040 > 5178 > 5286 > 5475 > 2263",
  "supplier": "AS WATSON (TRAD.HK LIM)",
  "inStock": "outOfStock",
  "onPromo": "",
  "mmkId": "",
  "productGroupId": "",
  "brandType": "Ander merk",
  "discount": "",
  "url": "/banzai-splash-sprinkler-waterpark/p/6458044",
  "listName": "Lister",
  "brand": "Overig",
  "mpOrigin": "Kruidvat",
  "mpShopId": "1",
  "isSponsored": "false",
  "categories": [
    {
      "id": 29536626,
      "name": "Speelgoed"
    },
    {
      "id": 30267084,
      "name": "Buitenspeelgoed"
    },
    {
      "id": 61683060,
      "name": "Waterspeelgoed"
    }
  ],
  "description": "335cm x 300cm x 64cm",
  "image": "/medias/sys_master/prd-images/hae/h79/45179857272862/prd-front-6458044-1_600x600/prd-front-6458044-1-600x600.jpg"
}