{
  "type": "product",
  "currency": "EUR",
  "itemName": "Dove Body Love Intense Care Bodylotion",
  "code": "2677109",
  "price": "8.99",
  "priceOriginal": "",
  "itemBgbcat": "2003 > 2059 > 2139 > 2342 > 3036 > 3484",
  "supplier": "UNILEVER NEDERLAND BV",
  "inStock": "inStock",
  "onPromo": "3030580",
  "mmkId": "3030580",
  "productGroupId": "490970",
  "brandType": "A of B merk",
  "discount": "",
  "url": "/dove-body-love-intense-care-bodylotion/p/2677109",
  "listName": "Lister",
  "brand": "Dove",
  "mpOrigin": "Kruidvat",
  "mpShopId": "1",
  "isSponsored": "false",
  "categories": [
    {
      "id": 29536623,
      "name": "Verzorging"
    },
    {
      "id": 30267046,
      "name": "Huidverzorging"
    },
    {
      "id": 30267194,
      "name": "Bodylotion"
    }
  ],
  "description": "400ml",
  "image": "/medias/sys_master/prd-images/h3b/hbd/34324564115486/prd-front-2677109-1_600x600/prd-front-2677109-1-600x600.jpg"
}