{
  "type": "product",
  "currency": "EUR",
  "itemName": "L'Oréal Paris Age Perfect Intensief Voedende Nachtcrème",
  "code": "2206086",
  "price": "13.2",
  "priceOriginal": "32.99",
  "itemBgbcat": "2002 > 2089 > 2256 > 2424 > 2832 > 5063",
  "supplier": "LOREAL NED BV",
  "inStock": "inStock",
  "onPromo": "3032539",
  "mmkId": "3032539",
  "productGroupId": "503042",
  "brandType": "A of B merk",
  "discount": "€ 19,79",
  "url": "/loreal-paris-age-perfect-intensief-voedende-nachtcreme/p/2206086",
  "listName": "Lister",
  "brand": "L'Oreal Paris",
  "mpOrigin": "Kruidvat",
  "mpShopId": "1",
  "isSponsored": "false",
  "categories": [
    {
      "id": 29536622,
      "name": "Beauty"
    },
    {
      "id": 30267042,
      "name": "Skincare"
    },
    {
      "id": 30267160,
      "name": "Nachtcreme"
    }
  ],
  "description": "50ml - Normale en rijpe huid",
  "image": "/medias/sys_master/prd-images/h3c/hf9/35155753140254/prd-front-2206086-1_600x600/prd-front-2206086-1-600x600.jpg"
}