{
  "type": "product",
  "currency": "EUR",
  "itemName": "DKNY Be Delicious Bodymist",
  "code": "5962444",
  "price": "11.99",
  "priceOriginal": "",
  "itemBgbcat": "2002 > 2080 > 2204 > 2549 > 3180 > 3486",
  "supplier": "LABORI INTERNATIONAL BV",
  "inStock": "inStock",
  "onPromo": "3031499",
  "mmkId": "3031499",
  "productGroupId": "498124",
  "brandType": "A of B merk",
  "discount": "",
  "url": "/dkny-be-delicious-bodymist/p/5962444",
  "listName": "Lister",
  "brand": "DKNY",
  "mpOrigin": "Kruidvat",
  "mpShopId": "1",
  "isSponsored": "false",
  "categories": [
    {
      "id": 29536622,
      "name": "Beauty"
    },
    {
      "id": 30267039,
      "name": "Parfum"
    },
    {
      "id": 30267158,
      "name": "Bodymist"
    }
  ],
  "description": "250ml",
  "image": "/medias/sys_master/prd-images/h33/hd0/28677601034270/prd-front-5962444-1_600x600/prd-front-5962444-1-600x600.jpg"
}