{
  "type": "product",
  "currency": "EUR",
  "itemName": "Zwitsal Haarlotion",
  "code": "6310750",
  "price": "4.49",
  "priceOriginal": "",
  "itemBgbcat": "2001 > 2031 > 2126 > 2322 > 2721 > 3424",
  "supplier": "UNILEVER NEDERLAND BV",
  "inStock": "outOfStock",
  "onPromo": "",
  "mmkId": "",
  "productGroupId": "",
  "brandType": "A of B merk",
  "discount": "",
  "url": "/zwitsal-haarlotion/p/6310750",
  "listName": "Lister",
  "brand": "Zwitsal",
  "mpOrigin": "Kruidvat",
  "mpShopId": "1",
  "isSponsored": "false",
  "categories": [
    {
      "id": 29536625,
      "name": "Baby"
    },
    {
      "id": 30267067,
      "name": "Babyverzorging"
    },
    {
      "id": 30267332,
      "name": "Baby haarverzorging"
    },
    {
      "id": 30267572,
      "name": "Baby haarlotion"
    }
  ],
  "description": "200ml",
  "image": "/medias/sys_master/prd-images/hce/hc7/34714122977310/prd-front-6310750-1_600x600/prd-front-6310750-1-600x600.jpg"
}