{
  "type": "product",
  "currency": "EUR",
  "itemName": "Goliath KennisKoord Het Touwtrek Trivia Spel",
  "code": "6263444",
  "price": "7.99",
  "priceOriginal": "",
  "itemBgbcat": "5921 > 6018 > 2181 > 5162 > 5217 > 5406",
  "supplier": "GOLIATH B.V.",
  "inStock": "inStock",
  "onPromo": "",
  "mmkId": "",
  "productGroupId": "",
  "brandType": "A of B merk",
  "discount": "",
  "url": "/goliath-kenniskoord-het-touwtrek-trivia-spel/p/6263444",
  "listName": "Lister",
  "brand": "Goliath",
  "mpOrigin": "Kruidvat",
  "mpShopId": "1",
  "isSponsored": "false",
  "categories": [
    {
      "id": 29536626,
      "name": "Speelgoed"
    },
    {
      "id": 49281487,
      "name": "Kaartspellen"
    }
  ],
  "description": "Nederlandstalig spel",
  "image": "/medias/sys_master/prd-images/h51/hcf/33752616828958/prd-front-6263444-1_600x600/prd-front-6263444-1-600x600.jpg"
}