{
  "type": "product",
  "currency": "EUR",
  "itemName": "Bumba Torenhoog Stapelblokken",
  "code": "6197280",
  "price": "4.99",
  "priceOriginal": "",
  "itemBgbcat": "5921 > 2096 > 2132 > 2331 > 2731 > 3434",
  "supplier": "STUDIO 100 NV",
  "inStock": "inStock",
  "onPromo": "",
  "mmkId": "",
  "productGroupId": "",
  "brandType": "A of B merk",
  "discount": "",
  "url": "/bumba-torenhoog-stapelblokken/p/6197280",
  "listName": "Lister",
  "brand": "Bumba",
  "mpOrigin": "Kruidvat",
  "mpShopId": "1",
  "isSponsored": "false",
  "categories": [
    {
      "id": 29536626,
      "name": "Speelgoed"
    },
    {
      "id": 30267077,
      "name": "Baby- en peuterspeelgoed"
    },
    {
      "id": 69053992,
      "name": "Bouwen"
    }
  ],
  "description": "",
  "image": "/medias/sys_master/prd-images/hf3/hd8/32403064913950/prd-front-6197280-1_600x600/prd-front-6197280-1-600x600.jpg"
}