{
  "type": "product",
  "currency": "EUR",
  "itemName": "Gliss Liquid Silk Anti-Klitspray",
  "code": "1217693",
  "price": "7.99",
  "priceOriginal": "",
  "itemBgbcat": "2003 > 2058 > 2186 > 6689 > 6694 > 2835",
  "supplier": "HENKEL NEDERLAND BV U-K",
  "inStock": "inStock",
  "onPromo": "3032854",
  "mmkId": "3032854",
  "productGroupId": "500969",
  "brandType": "A of B merk",
  "discount": "",
  "url": "/gliss-liquid-silk-anti-klitspray/p/1217693",
  "listName": "Lister",
  "brand": "Gliss",
  "mpOrigin": "Kruidvat",
  "mpShopId": "1",
  "isSponsored": "false",
  "categories": [
    {
      "id": 29536623,
      "name": "Verzorging"
    },
    {
      "id": 30267056,
      "name": "Haarverzorging"
    },
    {
      "id": 49213322,
      "name": "Anti-klitspray"
    }
  ],
  "description": "200ml",
  "image": "/medias/sys_master/prd-images/hf5/h77/33762492612638/prd-front-1217693-1_600x600/prd-front-1217693-1-600x600.jpg"
}