{
  "type": "product",
  "currency": "EUR",
  "itemName": "Taft Overnight Fresh Wonder Droogshampoo Mousse",
  "code": "5951832",
  "price": "6.49",
  "priceOriginal": "",
  "itemBgbcat": "2003 > 2058 > 2188 > 2392 > 6398 > 6082",
  "supplier": "HENKEL NEDERLAND BV U-K",
  "inStock": "inStock",
  "onPromo": "3028279",
  "mmkId": "3028279",
  "productGroupId": "466370",
  "brandType": "A of B merk",
  "discount": "",
  "url": "/taft-overnight-fresh-wonder-droogshampoo-mousse/p/5951832",
  "listName": "Lister",
  "brand": "Taft",
  "mpOrigin": "Kruidvat",
  "mpShopId": "1",
  "isSponsored": "false",
  "categories": [
    {
      "id": 29536623,
      "name": "Verzorging"
    },
    {
      "id": 30267056,
      "name": "Haarverzorging"
    },
    {
      "id": 30267250,
      "name": "Droogshampoo"
    }
  ],
  "description": "150ml",
  "image": "/medias/sys_master/prd-images/he1/h8d/33736122564638/prd-front-5951832-1_600x600/prd-front-5951832-1-600x600.jpg"
}