{
  "type": "product",
  "currency": "EUR",
  "itemName": "Jumbo Premium Collection Deer Family Puzzel",
  "code": "6224216",
  "price": "16.99",
  "priceOriginal": "",
  "itemBgbcat": "5921 > 6018 > 2181 > 5166 > 5237 > 5426",
  "supplier": "JUMBO NL BV",
  "inStock": "inStock",
  "onPromo": "3029932",
  "mmkId": "3029932",
  "productGroupId": "487703",
  "brandType": "A of B merk",
  "discount": "",
  "url": "/jumbo-premium-collection-deer-family-puzzel/p/6224216",
  "listName": "Lister",
  "brand": "Jumbo",
  "mpOrigin": "Kruidvat",
  "mpShopId": "1",
  "isSponsored": "false",
  "categories": [
    {
      "id": 29536626,
      "name": "Speelgoed"
    },
    {
      "id": 90172085,
      "name": "Puzzels"
    }
  ],
  "description": "3000 stukjes",
  "image": "/medias/sys_master/prd-images/h51/h06/32898113404958/prd-front-6224216-1_600x600/prd-front-6224216-1-600x600.jpg"
}