{
  "type": "product",
  "currency": "EUR",
  "itemName": "LEGO Technic 42212 Ferrari Fxx K",
  "code": "6346674",
  "price": "54.99",
  "priceOriginal": "",
  "itemBgbcat": "5921 > 6040 > 2141 > 2346 > 2747 > 3455",
  "supplier": "LEGO BENELUX BV (BNL)",
  "inStock": "outOfStock",
  "onPromo": "",
  "mmkId": "",
  "productGroupId": "",
  "brandType": "A of B merk",
  "discount": "",
  "url": "/lego-technic-42212-ferrari-fxx-k/p/6346674",
  "listName": "Lister",
  "brand": "LEGO Technic",
  "mpOrigin": "Kruidvat",
  "mpShopId": "1",
  "isSponsored": "false",
  "categories": [
    {
      "id": 29536626,
      "name": "Speelgoed"
    },
    {
      "id": 30267076,
      "name": "LEGO"
    },
    {
      "id": 30267381,
      "name": "LEGO Technic"
    }
  ],
  "description": "",
  "image": "/medias/sys_master/prd-images/h91/h78/35037847650334/prd-front-6346674-1_600x600/prd-front-6346674-1-600x600.jpg"
}