{
  "type": "product",
  "currency": "EUR",
  "itemName": "Essence Crystal Crush 01 Diamond Dew Dewy Highlighter Cream",
  "code": "6445997",
  "price": "3.49",
  "priceOriginal": "",
  "itemBgbcat": "2002 > 2069 > 2210 > 2378 > 2819 > 6780",
  "supplier": "COSNOVA GMBH (BNL)",
  "inStock": "inStock",
  "onPromo": "",
  "mmkId": "",
  "productGroupId": "",
  "brandType": "Exclusief merk",
  "discount": "",
  "url": "/essence-crystal-crush-01-diamond-dew-dewy-highlighter-cream/p/6445997",
  "listName": "Lister",
  "brand": "Essence",
  "mpOrigin": "Kruidvat",
  "mpShopId": "1",
  "isSponsored": "false",
  "categories": [
    {
      "id": 29536622,
      "name": "Beauty"
    },
    {
      "id": 30267038,
      "name": "Make-up"
    },
    {
      "id": 30267146,
      "name": "Highlighter"
    }
  ],
  "description": "14ml",
  "image": "/medias/sys_master/prd-images/h76/ha6/45300163084318/prd-front-6445997-1_600x600/prd-front-6445997-1-600x600.jpg"
}