{
  "type": "product",
  "currency": "EUR",
  "itemName": "Libresse Ultra Normal Multistyle Maandverband",
  "code": "6362039",
  "price": "2.89",
  "priceOriginal": "",
  "itemBgbcat": "2003 > 2065 > 2205 > 2463 > 3261 > 4159",
  "supplier": "ESSITY",
  "inStock": "outOfStock",
  "onPromo": "3033298",
  "mmkId": "3033298",
  "productGroupId": "508691",
  "brandType": "A of B merk",
  "discount": "",
  "url": "/libresse-ultra-normal-multistyle-maandverband/p/6362039",
  "listName": "Lister",
  "brand": "Libresse",
  "mpOrigin": "Kruidvat",
  "mpShopId": "1",
  "isSponsored": "false",
  "categories": [
    {
      "id": 29536623,
      "name": "Verzorging"
    },
    {
      "id": 30267051,
      "name": "Intieme verzorging"
    },
    {
      "id": 30267219,
      "name": "Maandverband"
    }
  ],
  "description": "10 stuks",
  "image": "/medias/sys_master/prd-images/hc6/hc9/44000515686430/prd-front-6362039-1_600x600/prd-front-6362039-1-600x600.jpg"
}