{
  "type": "product",
  "currency": "EUR",
  "itemName": "NIVEA Hold 5 Ultra Strong Styling Hairspray",
  "code": "30692",
  "price": "7.29",
  "priceOriginal": "",
  "itemBgbcat": "2003 > 2058 > 2188 > 2392 > 3049 > 3696",
  "supplier": "BEIERSDORF NV NL",
  "inStock": "inStock",
  "onPromo": "3032014",
  "mmkId": "3032014",
  "productGroupId": "489244",
  "brandType": "A of B merk",
  "discount": "",
  "url": "/nivea-hold-5-ultra-strong-styling-hairspray/p/30692",
  "listName": "Lister",
  "brand": "Nivea",
  "mpOrigin": "Kruidvat",
  "mpShopId": "1",
  "isSponsored": "false",
  "categories": [
    {
      "id": 29536623,
      "name": "Verzorging"
    },
    {
      "id": 30267249,
      "name": "Haarstylingproducten"
    },
    {
      "id": 30267492,
      "name": "Haarlak"
    }
  ],
  "description": "250ml",
  "image": "/medias/sys_master/prd-images/h5f/hac/34030329757726/prd-front-30692-1_600x600/prd-front-30692-1-600x600.jpg"
}