{
  "type": "product",
  "currency": "EUR",
  "itemName": "Bioré Anti-Puistjes Cleanser met Houtskool",
  "code": "4362212",
  "price": "10.99",
  "priceOriginal": "",
  "itemBgbcat": "2002 > 2089 > 2256 > 6702 > 2804 > 6703",
  "supplier": "GUHL IKEBANA COSMETICS",
  "inStock": "inStock",
  "onPromo": "3030425",
  "mmkId": "3030425",
  "productGroupId": "499063",
  "brandType": "A of B merk",
  "discount": "",
  "url": "/biore-anti-puistjes-cleanser-met-houtskool/p/4362212",
  "listName": "Lister",
  "brand": "Bioré",
  "mpOrigin": "Kruidvat",
  "mpShopId": "1",
  "isSponsored": "false",
  "categories": [
    {
      "id": 29536622,
      "name": "Beauty"
    },
    {
      "id": 30267042,
      "name": "Skincare"
    },
    {
      "id": 30267165,
      "name": "Gezichtsreiniging"
    },
    {
      "id": 30267474,
      "name": "Reinigingsgel"
    }
  ],
  "description": "200ml - Onzuivere huid",
  "image": "/medias/sys_master/prd-images/h96/hed/34536546369566/prd-front-4362212-1_600x600/prd-front-4362212-1-600x600.jpg"
}