{
  "type": "product",
  "currency": "EUR",
  "itemName": "Difrax Natural 18+M Fopspeen",
  "code": "5439554",
  "price": "5.99",
  "priceOriginal": "",
  "itemBgbcat": "2001 > 2033 > 2128 > 2417 > 2871 > 6356",
  "supplier": "DIFRAX BV",
  "inStock": "inStock",
  "onPromo": "3028963",
  "mmkId": "3028963",
  "productGroupId": "478657",
  "brandType": "A of B merk",
  "discount": "",
  "url": "/difrax-natural-18m-fopspeen/p/5439554",
  "listName": "Lister",
  "brand": "Difrax",
  "mpOrigin": "Kruidvat",
  "mpShopId": "1",
  "isSponsored": "false",
  "categories": [
    {
      "id": 29536625,
      "name": "Baby"
    },
    {
      "id": 30267073,
      "name": "Babyvoedingsaccessoires"
    },
    {
      "id": 30267354,
      "name": "Fopspenen"
    }
  ],
  "description": "donkerblauw",
  "image": "/medias/sys_master/prd-images/h75/ha7/29462242787358/prd-front-5439554-1_600x600/prd-front-5439554-1-600x600.jpg"
}