{
  "type": "product",
  "currency": "EUR",
  "itemName": "Catrice 020 Ash Brown Wenkbrauwpoeder Set Waterproof",
  "code": "5591916",
  "price": "3.99",
  "priceOriginal": "",
  "itemBgbcat": "2002 > 2069 > 2210 > 2422 > 6131 > 6132",
  "supplier": "COSNOVA GMBH (BNL)",
  "inStock": "inStock",
  "onPromo": "3028395",
  "mmkId": "3028395",
  "productGroupId": "472690",
  "brandType": "Exclusief merk",
  "discount": "",
  "url": "/catrice-020-ash-brown-wenkbrauwpoeder-set-waterproof/p/5591916",
  "listName": "Lister",
  "brand": "Catrice",
  "mpOrigin": "Kruidvat",
  "mpShopId": "1",
  "isSponsored": "false",
  "categories": [
    {
      "id": 29536622,
      "name": "Beauty"
    },
    {
      "id": 30267038,
      "name": "Make-up"
    },
    {
      "id": 30267149,
      "name": "Wenkbrauw make-up"
    },
    {
      "id": 30267466,
      "name": "Wenkbrauwpoeder"
    }
  ],
  "description": "4g"
}