{
  "type": "product",
  "currency": "EUR",
  "itemName": "Catrice Holiday Skin 010 Forever Summer Glow Self Tanning Drops",
  "code": "6344728",
  "price": "6.99",
  "priceOriginal": "",
  "itemBgbcat": "2002 > 2069 > 2210 > 2378 > 2819 > 3560",
  "supplier": "COSNOVA GMBH (BNL)",
  "inStock": "inStock",
  "onPromo": "3005772",
  "mmkId": "3005772",
  "productGroupId": "",
  "brandType": "Exclusief merk",
  "discount": "",
  "url": "/catrice-holiday-skin-010-forever-summer-glow-self-tanning-drops/p/6344728",
  "listName": "Lister",
  "brand": "Catrice",
  "mpOrigin": "Kruidvat",
  "mpShopId": "1",
  "isSponsored": "false",
  "categories": [
    {
      "id": 29536623,
      "name": "Verzorging"
    },
    {
      "id": 30267050,
      "name": "Zonbescherming"
    },
    {
      "id": 30267216,
      "name": "Zelfbruiners"
    }
  ],
  "description": "30ml"
}