{
  "type": "product",
  "currency": "EUR",
  "itemName": "Trekpleister Espressobonen",
  "code": "5437979",
  "price": "14.99",
  "priceOriginal": "",
  "itemBgbcat": "2004 > 2084 > 2246 > 2373 > 6643 > 6644",
  "supplier": "UCC COFFEE BENELUX BV",
  "inStock": "inStock",
  "onPromo": "3028546",
  "mmkId": "3028546",
  "productGroupId": "474810",
  "brandType": "Eigen merk",
  "discount": "",
  "url": "/trekpleister-espressobonen/p/5437979",
  "listName": "Lister",
  "brand": "Trekpleister",
  "mpOrigin": "Kruidvat",
  "mpShopId": "1",
  "isSponsored": "false",
  "categories": [
    {
      "id": 29536631,
      "name": "Huishouden"
    },
    {
      "id": 30267127,
      "name": "Eten en drinken"
    },
    {
      "id": 30267443,
      "name": "Koffie"
    }
  ],
  "description": "1000g"
}