{
  "type": "product",
  "currency": "EUR",
  "itemName": "Dove Body Love Light Hydration One Cream",
  "code": "5562929",
  "price": "7.79",
  "priceOriginal": "",
  "itemBgbcat": "2003 > 2059 > 2139 > 2342 > 3036 > 3484",
  "supplier": "UNILEVER NEDERLAND BV",
  "inStock": "inStock",
  "onPromo": "3031469",
  "mmkId": "3031469",
  "productGroupId": "489599",
  "brandType": "A of B merk",
  "discount": "",
  "url": "/dove-body-love-light-hydration-one-cream/p/5562929",
  "listName": "Lister",
  "brand": "Dove",
  "mpOrigin": "Kruidvat",
  "mpShopId": "1",
  "isSponsored": "false",
  "categories": [
    {
      "id": 29536623,
      "name": "Verzorging"
    },
    {
      "id": 30267046,
      "name": "Huidverzorging"
    },
    {
      "id": 30267198,
      "name": "Bodycremes"
    }
  ],
  "description": "250ml",
  "image": "/medias/sys_master/prd-images/hd3/h1b/44337875288094/prd-front-5562929-1_600x600/prd-front-5562929-1-600x600.jpg"
}