{
  "type": "product",
  "currency": "EUR",
  "itemName": "Veet Expert Ontharingscrème voor Lichaam en Benen",
  "code": "5844319",
  "price": "9.79",
  "priceOriginal": "",
  "itemBgbcat": "2003 > 2088 > 5075 > 2399 > 2839 > 3579",
  "supplier": "RECKITT BENCKISER B.V",
  "inStock": "inStock",
  "onPromo": "3030370",
  "mmkId": "3030370",
  "productGroupId": "486749",
  "brandType": "A of B merk",
  "discount": "",
  "url": "/veet-expert-ontharingscreme-voor-lichaam-en-benen/p/5844319",
  "listName": "Lister",
  "brand": "Veet",
  "mpOrigin": "Kruidvat",
  "mpShopId": "1",
  "isSponsored": "false",
  "categories": [
    {
      "id": 29536623,
      "name": "Verzorging"
    },
    {
      "id": 30267053,
      "name": "Scheren en ontharen"
    },
    {
      "id": 30267239,
      "name": "Ontharingscreme, wax en hars"
    }
  ],
  "description": "200ml"
}