{
  "type": "product",
  "currency": "EUR",
  "itemName": "Oral-B Pro-Expert Gezond Wit Tandpasta",
  "code": "3176986",
  "price": "4.89",
  "priceOriginal": "",
  "itemBgbcat": "2003 > 2075 > 2223 > 2639 > 3323 > 6336",
  "supplier": "PROCTER & GAMBLE NL BV",
  "inStock": "inStock",
  "onPromo": "3028739",
  "mmkId": "3028739",
  "productGroupId": "477324",
  "brandType": "A of B merk",
  "discount": "",
  "url": "/oral-b-pro-expert-gezond-wit-tandpasta/p/3176986",
  "listName": "Lister",
  "brand": "Oral B",
  "mpOrigin": "Kruidvat",
  "mpShopId": "1",
  "isSponsored": "false",
  "categories": [
    {
      "id": 29536623,
      "name": "Verzorging"
    },
    {
      "id": 30267052,
      "name": "Mondverzorging"
    },
    {
      "id": 30267231,
      "name": "Tandpasta"
    }
  ],
  "description": "75ml",
  "image": "/medias/sys_master/prd-images/h67/h8b/33562584121374/prd-front-3176986-1_600x600/prd-front-3176986-1-600x600.jpg"
}