{
  "type": "product",
  "currency": "EUR",
  "itemName": "Garnier Fructis Pineapple Hair Food Conditioner",
  "code": "5802522",
  "price": "8.49",
  "priceOriginal": "",
  "itemBgbcat": "2003 > 2058 > 2186 > 2391 > 2836 > 3914",
  "supplier": "LOREAL NED BV",
  "inStock": "inStock",
  "onPromo": "3032854",
  "mmkId": "3032854",
  "productGroupId": "500969",
  "brandType": "A of B merk",
  "discount": "",
  "url": "/garnier-fructis-pineapple-hair-food-conditioner/p/5802522",
  "listName": "Lister",
  "brand": "Fructis",
  "mpOrigin": "Kruidvat",
  "mpShopId": "1",
  "isSponsored": "false",
  "categories": [
    {
      "id": 29536623,
      "name": "Verzorging"
    },
    {
      "id": 30267056,
      "name": "Haarverzorging"
    },
    {
      "id": 30267252,
      "name": "Conditioner"
    }
  ],
  "description": "350ml",
  "image": "/medias/sys_master/prd-images/hf1/h87/30139775582238/prd-front-5802522-1_600x600/prd-front-5802522-1-600x600.jpg"
}