{
  "type": "product",
  "currency": "EUR",
  "itemName": "Garnier SkinActive Hydra Bomb Tissuemasker",
  "code": "4052245",
  "price": "3.49",
  "priceOriginal": "",
  "itemBgbcat": "2002 > 2089 > 2256 > 2301 > 2775 > 3542",
  "supplier": "LOREAL NED BV",
  "inStock": "inStock",
  "onPromo": "3033046",
  "mmkId": "3033046",
  "productGroupId": "506225",
  "brandType": "A of B merk",
  "discount": "",
  "url": "/garnier-skinactive-hydra-bomb-tissuemasker/p/4052245",
  "listName": "Lister",
  "brand": "Garnier Skin Naturals",
  "mpOrigin": "Kruidvat",
  "mpShopId": "1",
  "isSponsored": "false",
  "categories": [
    {
      "id": 29536622,
      "name": "Beauty"
    },
    {
      "id": 30267042,
      "name": "Skincare"
    },
    {
      "id": 30267164,
      "name": "Gezichtsmaskers"
    }
  ],
  "description": "32g - Droge huid",
  "image": "/medias/sys_master/prd-images/hb4/h5f/35156052246558/prd-front-4052245-1_600x600/prd-front-4052245-1-600x600.jpg"
}