{
  "type": "product",
  "currency": "EUR",
  "itemName": "NIVEA Q10 Power Anti-Rimpel Dagcrème",
  "code": "1300552",
  "price": "23.99",
  "priceOriginal": "",
  "itemBgbcat": "2002 > 2089 > 2256 > 2424 > 2832 > 3574",
  "supplier": "BEIERSDORF NV NL",
  "inStock": "inStock",
  "onPromo": "3028927",
  "mmkId": "3028927",
  "productGroupId": "476596",
  "brandType": "A of B merk",
  "discount": "",
  "url": "/nivea-q10-power-anti-rimpel-dagcreme/p/1300552",
  "listName": "Lister",
  "brand": "Nivea Skincare",
  "mpOrigin": "Kruidvat",
  "mpShopId": "1",
  "isSponsored": "false",
  "categories": [
    {
      "id": 29536622,
      "name": "Beauty"
    },
    {
      "id": 30267042,
      "name": "Skincare"
    },
    {
      "id": 30267159,
      "name": "Dagcreme"
    }
  ],
  "description": "50ml - Alle huidtypen"
}