{
  "type": "product",
  "currency": "EUR",
  "itemName": "Garnier SkinActive Sinaasappel & Hyaluronzuur Oog Tissuemasker",
  "code": "4418828",
  "price": "2.79",
  "priceOriginal": "",
  "itemBgbcat": "2002 > 2089 > 2256 > 2301 > 2775 > 3542",
  "supplier": "L'OREAL NED B.V.",
  "inStock": "inStock",
  "onPromo": "3033189",
  "mmkId": "3033189",
  "productGroupId": "514184",
  "brandType": "A of B merk",
  "discount": "",
  "url": "/garnier-skinactive-sinaasappel-hyaluronzuur-oog-tissuemasker/p/4418828",
  "listName": "Lister",
  "brand": "Garnier Skin Naturals",
  "mpOrigin": "Kruidvat",
  "mpShopId": "1",
  "isSponsored": "false",
  "categories": [
    {
      "id": 29536622,
      "name": "Beauty"
    },
    {
      "id": 30267042,
      "name": "Skincare"
    },
    {
      "id": 30267164,
      "name": "Gezichtsmaskers"
    }
  ],
  "description": "",
  "image": "/medias/sys_master/prd-images/h92/h57/35156353843230/prd-front-4418828-1_600x600/prd-front-4418828-1-600x600.jpg"
}