{
  "type": "product",
  "currency": "EUR",
  "itemName": "Catrice Endless Matte 040 Wifey Liquid Lippenstift",
  "code": "6104852",
  "price": "4.99",
  "priceOriginal": "",
  "itemBgbcat": "2002 > 2069 > 2210 > 2468 > 2994 > 3821",
  "supplier": "COSNOVA GMBH (BNL)",
  "inStock": "inStock",
  "onPromo": "3033699",
  "mmkId": "3033699",
  "productGroupId": "516941",
  "brandType": "Exclusief merk",
  "discount": "",
  "url": "/catrice-endless-matte-040-wifey-liquid-lippenstift/p/6104852",
  "listName": "Lister",
  "brand": "Catrice",
  "mpOrigin": "Kruidvat",
  "mpShopId": "1",
  "isSponsored": "false",
  "categories": [
    {
      "id": 29536622,
      "name": "Beauty"
    },
    {
      "id": 30267038,
      "name": "Make-up"
    },
    {
      "id": 88118383,
      "name": "Lipmake-up"
    },
    {
      "id": 30267139,
      "name": "Lipstick"
    }
  ],
  "description": "4,5ml",
  "image": "/medias/sys_master/prd-images/h22/he6/35009258881054/prd-front-6104852-1_600x600/prd-front-6104852-1-600x600.jpg"
}