{
  "type": "product",
  "currency": "EUR",
  "itemName": "Disney Stitch Gevulde Etui",
  "code": "6182909",
  "price": "6.99",
  "priceOriginal": "",
  "itemBgbcat": "5921 > 6040 > 2176 > 2430 > 2915 > 3710",
  "supplier": "SPEELGOEDLAND",
  "inStock": "inStock",
  "onPromo": "3032695",
  "mmkId": "3032695",
  "productGroupId": "500860",
  "brandType": "A of B merk",
  "discount": "",
  "url": "/disney-stitch-gevulde-etui/p/6182909",
  "listName": "Lister",
  "brand": "Stitch",
  "mpOrigin": "Kruidvat",
  "mpShopId": "1",
  "isSponsored": "false",
  "categories": [
    {
      "id": 29536626,
      "name": "Speelgoed"
    },
    {
      "id": 30267081,
      "name": "Knutselen"
    }
  ],
  "description": ""
}