{
  "type": "product",
  "currency": "EUR",
  "itemName": "My Haircandy Vierkante Haarklem",
  "code": "5860748",
  "price": "0.0",
  "priceOriginal": "",
  "itemBgbcat": "2002 > 6674 > 2189 > 2333 > 2735 > 6323",
  "supplier": "LITTLE CONCEPTS NETTO",
  "inStock": "outOfStock",
  "onPromo": "",
  "mmkId": "",
  "productGroupId": "",
  "brandType": "A of B merk",
  "discount": "",
  "url": "/my-haircandy-vierkante-haarklem/p/5860748",
  "listName": "Lister",
  "brand": "My Haircandy",
  "mpOrigin": "Kruidvat",
  "mpShopId": "1",
  "isSponsored": "false",
  "categories": [
    {
      "id": 29536622,
      "name": "Beauty"
    },
    {
      "id": 30267044,
      "name": "Haaraccessoires"
    },
    {
      "id": 30267183,
      "name": "Haarklemmen"
    }
  ],
  "description": "bruin",
  "image": "/medias/sys_master/prd-images/hb5/h41/28949813755934/prd-front-5860748-1_600x600/prd-front-5860748-1-600x600.jpg"
}