{
  "type": "product",
  "currency": "EUR",
  "itemName": "Alpine PartyPlug Pro Oordoppen",
  "code": "6265740",
  "price": "17.21",
  "priceOriginal": "22.95",
  "itemBgbcat": "2006 > 5048 > 2280 > 6717 > 6718 > 6719",
  "supplier": "ALPINE NEDERLAND BV",
  "inStock": "inStock",
  "onPromo": "3033865",
  "mmkId": "3033865",
  "productGroupId": "512735",
  "brandType": "A of B merk",
  "discount": "€ 5,74",
  "url": "/alpine-partyplug-pro-oordoppen/p/6265740",
  "listName": "Lister",
  "brand": "Alpine",
  "mpOrigin": "Kruidvat",
  "mpShopId": "1",
  "isSponsored": "false",
  "categories": [
    {
      "id": 29536624,
      "name": "Gezondheid"
    },
    {
      "id": 30267057,
      "name": "Zelfzorg"
    },
    {
      "id": 30267257,
      "name": "Oor en mond"
    },
    {
      "id": 30267507,
      "name": "Oordoppen"
    },
    {
      "id": 117396366,
      "name": "Muziek oordoppen"
    }
  ],
  "description": "",
  "image": "/medias/sys_master/prd-images/h01/h5e/33465409896478/prd-front-6265740-1_600x600/prd-front-6265740-1-600x600.jpg"
}