{
  "type": "product",
  "currency": "EUR",
  "itemName": "Aunt Jackie's Kids Soft & Sassy Conditioner",
  "code": "5616766",
  "price": "8.99",
  "priceOriginal": "",
  "itemBgbcat": "2003 > 2058 > 2186 > 5866 > 6700 > 5896",
  "supplier": "YARI BV",
  "inStock": "inStock",
  "onPromo": "3029587",
  "mmkId": "3029587",
  "productGroupId": "474304",
  "brandType": "A of B merk",
  "discount": "",
  "url": "/aunt-jackies-kids-soft-sassy-conditioner/p/5616766",
  "listName": "Lister",
  "brand": "Aunt Jackie's",
  "mpOrigin": "Kruidvat",
  "mpShopId": "1",
  "isSponsored": "false",
  "categories": [
    {
      "id": 29536623,
      "name": "Verzorging"
    },
    {
      "id": 30267056,
      "name": "Haarverzorging"
    },
    {
      "id": 30267252,
      "name": "Conditioner"
    }
  ],
  "description": "434ml",
  "image": "/medias/sys_master/prd-images/h80/h8e/28569188597790/prd-front-5616766-1_600x600/prd-front-5616766-1-600x600.jpg"
}