{
  "type": "product",
  "currency": "EUR",
  "itemName": "Trekpleister Valeriaan Tabletten",
  "code": "1051604",
  "price": "5.99",
  "priceOriginal": "",
  "itemBgbcat": "2006 > 5048 > 2280 > 6207 > 6225 > 6303",
  "supplier": "HERKEL BV",
  "inStock": "inStock",
  "onPromo": "3032323",
  "mmkId": "3032323",
  "productGroupId": "500017",
  "brandType": "Eigen merk",
  "discount": "",
  "url": "/trekpleister-valeriaan-tabletten/p/1051604",
  "listName": "Lister",
  "brand": "Trekpleister",
  "mpOrigin": "Kruidvat",
  "mpShopId": "1",
  "isSponsored": "false",
  "categories": [
    {
      "id": 29536624,
      "name": "Gezondheid"
    },
    {
      "id": 30267058,
      "name": "Voedingssupplementen"
    },
    {
      "id": 30267281,
      "name": "Rust en ontspanning"
    }
  ],
  "description": "60 stuks",
  "image": "/medias/sys_master/prd-images/h2e/hda/28549594120222/prd-front-1051604-1_600x600/prd-front-1051604-1-600x600.jpg"
}