{
  "type": "product",
  "currency": "EUR",
  "itemName": "Catrice Soft Blur 010 Lychee Lush Powder Blush",
  "code": "6465492",
  "price": "3.49",
  "priceOriginal": "",
  "itemBgbcat": "2002 > 2069 > 2210 > 2378 > 2819 > 5687",
  "supplier": "COSNOVA GMBH (BNL)",
  "inStock": "inStock",
  "onPromo": "3005772",
  "mmkId": "3005772",
  "productGroupId": "",
  "brandType": "Exclusief merk",
  "discount": "",
  "url": "/catrice-soft-blur-010-lychee-lush-powder-blush/p/6465492",
  "listName": "Lister",
  "brand": "Catrice",
  "mpOrigin": "Kruidvat",
  "mpShopId": "1",
  "isSponsored": "false",
  "categories": [
    {
      "id": 29536622,
      "name": "Beauty"
    },
    {
      "id": 30267038,
      "name": "Make-up"
    },
    {
      "id": 30267147,
      "name": "Blush"
    }
  ],
  "description": "5g",
  "image": "/medias/sys_master/prd-images/h80/h66/46725593104414/temp-prd-front-6465492-1_600x600/temp-prd-front-6465492-1-600x600.jpg"
}